lightblue/__init__.py
lightblue/common.py
lightblue/custombeanbag.py
lightblue/entity.py
lightblue/query.py
lightblue/selection.py
lightblue/service.py
python_lightblue-1.0.3.dist-info/LICENSE
python_lightblue-1.0.3.dist-info/METADATA
python_lightblue-1.0.3.dist-info/WHEEL
python_lightblue-1.0.3.dist-info/top_level.txt
python_lightblue-1.0.3.dist-info/RECORD
