Metadata-Version: 2.1
Name: python-lightblue
Version: 1.0.3
Summary: A Python API for Lightblue database.
Home-page: https://github.com/redhat-aqe/python-lightblue
Author: Ales Raszka, Mark Birger, Lukáš Krajíček
Author-email: araszka@redhat.com, mbirger@redhat.com, lkrajice@redhat.com
License: GPLv3
Platform: UNKNOWN
Classifier: Development Status :: 5 - Production/Stable
Classifier: Environment :: Console
Classifier: Intended Audience :: Developers
Classifier: License :: OSI Approved :: GNU General Public License v3 (GPLv3)
Classifier: Operating System :: OS Independent
Classifier: Programming Language :: Python :: 2.7
Classifier: Programming Language :: Python :: 3.6
Classifier: Topic :: Database
Classifier: Topic :: Software Development :: Libraries :: Python Modules
